odoo/addons/base_user_chatter/README.rst
odoo/addons/base_user_chatter/__init__.py
odoo/addons/base_user_chatter/__manifest__.py
odoo/addons/base_user_chatter/i18n/base_user_chatter.pot
odoo/addons/base_user_chatter/models/__init__.py
odoo/addons/base_user_chatter/models/res_users.py
odoo/addons/base_user_chatter/readme/DESCRIPTION.md
odoo/addons/base_user_chatter/static/description/icon.png
odoo/addons/base_user_chatter/static/description/index.html
odoo/addons/base_user_chatter/views/res_users_views.xml
odoo_addon_base_user_chatter-16.0.1.0.0.2.dist-info/METADATA
odoo_addon_base_user_chatter-16.0.1.0.0.2.dist-info/WHEEL
odoo_addon_base_user_chatter-16.0.1.0.0.2.dist-info/top_level.txt
odoo_addon_base_user_chatter-16.0.1.0.0.2.dist-info/RECORD
